README.rst
setup.py
gitlab_freak/__init__.py
gitlab_freak/helpers.py
gitlab_freak/models.py
gitlab_freak.egg-info/PKG-INFO
gitlab_freak.egg-info/SOURCES.txt
gitlab_freak.egg-info/dependency_links.txt
gitlab_freak.egg-info/not-zip-safe
gitlab_freak.egg-info/requires.txt
gitlab_freak.egg-info/top_level.txt
gitlab_freak/scripts/gitlab-freak-init-db.py
gitlab_freak/scripts/gitlab-freak-run.py