Metadata-Version: 1.1
Name: gitlab-freak
Version: 1.0.0a1
Summary: A Flask server that allows you to interact         with Trello from your own Gitlab.
Home-page: https://github.com/Pegase745/gitlab-freak
Author: Michel Nemnom
Author-email: michel.nemnom+pypi@gmail.com
License: MIT
Keywords: gitlab trello
Platform: UNKNOWN
Classifier: Development Status :: 3 - Alpha
Classifier: Intended Audience :: Developers
Classifier: License :: OSI Approved :: MIT License
Classifier: Natural Language :: English
Classifier: Programming Language :: Python :: 2
Classifier: Programming Language :: Python :: 2.7
Classifier: Programming Language :: Python :: 3
Classifier: Programming Language :: Python :: 3.4
